Workbook

Sheet Capa
B2: PARECER TÉCNICO AUTOMOTIVO
B3: Qual carro comprar em cada orçamento
B6: Comparativo de 10 modelos · avaliação por manutenção, consumo e seguro · atualizado conforme a base de dados
B8: NAVEGAÇÃO
B10: 📊 Painel Geral
B13: ⚙️ Metodologia & Score
B16: 📋 Ranking Completo
B19: 💰 Comparativo por Faixa
B22: 🔎 Ficha Individual
B25: 📝 Parecer Técnico — Se eu fosse comprar
B28: 📚 Fontes e Notas
B32: Elaborado a partir de avaliação prática de modelos populares usados — uso pessoal.

Sheet Painel Geral
A1: ← Capa
B2: PAINEL GERAL
B3: Visão consolidada dos 10 modelos avaliados
B5: CARROS AVALIADOS | D5: SCORE MÉDIO | F5: MELHOR SCORE | H5: FAIXA MAIS BARATA
B6: =COUNTA('Base de Dados'!C5:C14) -> 10 | D6: =ROUND(AVERAGE('Base de Dados'!P5:P14),1) -> 7.9 | F6: =INDEX('Base de Dados'!C5:C14,MATCH(MAX('Base de Dados'!P5:P14),'Base de Dados'!P5:P14,0)) -> Honda Fit 2008/09 | H6: =INDEX('Base de Dados'!F5:F14,MATCH(MIN('Base de Dados'!D5:D14),'Base de Dados'!D5:D14,0)) -> Até R$30 mil
B7: modelos na base | D7: de 0 a 10 | F7: topo do ranking | H7: menor preço mínimo
B10: SCORE FINAL POR MODELO | F10: MODELOS POR FAIXA DE ORÇAMENTO | K10: Faixa | L10: Qtde
K11: Até R$30 mil | L11: =COUNTIF('Base de Dados'!Q5:Q14,K11) -> 2
K12: R$30–45 mil | L12: =COUNTIF('Base de Dados'!Q5:Q14,K12) -> 4
K13: R$45–60 mil | L13: =COUNTIF('Base de Dados'!Q5:Q14,K13) -> 4
K14: R$60 mil+ | L14: =COUNTIF('Base de Dados'!Q5:Q14,K14) -> 0
B29: TOP 3 DO RANKING GERAL
B30: Posição | C30: Modelo | D30: Faixa de preço | E30: Score
B31: 1 | C31: =INDEX('Base de Dados'!C5:C14,MATCH(1,'Base de Dados'!R5:R14,0)) -> Honda Fit 2008/09 | D31: =INDEX('Base de Dados'!F5:F14,MATCH(1,'Base de Dados'!R5:R14,0)) -> R$35–45 mil | E31: =INDEX('Base de Dados'!P5:P14,MATCH(1,'Base de Dados'!R5:R14,0)) -> 10
B32: 2 | C32: =INDEX('Base de Dados'!C5:C14,MATCH(2,'Base de Dados'!R5:R14,0)) -> Uno Firefly | D32: =INDEX('Base de Dados'!F5:F14,MATCH(2,'Base de Dados'!R5:R14,0)) -> R$35–45 mil | E32: =INDEX('Base de Dados'!P5:P14,MATCH(2,'Base de Dados'!R5:R14,0)) -> 10
B33: 3 | C33: =INDEX('Base de Dados'!C5:C14,MATCH(3,'Base de Dados'!R5:R14,0)) -> Corsa Max | D33: =INDEX('Base de Dados'!F5:F14,MATCH(3,'Base de Dados'!R5:R14,0)) -> Até R$30 mil | E33: =INDEX('Base de Dados'!P5:P14,MATCH(3,'Base de Dados'!R5:R14,0)) -> 9.3

Sheet Metodologia
A1: ← Capa
B2: METODOLOGIA DE PONTUAÇÃO (SCORE)
B3: Como as notas qualitativas viram uma nota final de 0 a 10 — pesos editáveis em azul.
B5: MANUTENÇÃO | C5: Nota | E5: CONSUMO | F5: Nota
B6: Muito baixa | C6: 5 | E6: Excelente | F6: 5
B7: Baixa | C7: 4 | E7: Boa | F7: 4
B8: Média | C8: 3 | E8: Média | F8: 3
B9: Alta | C9: 2 | E9: Ruim | F9: 2
B10: Muito alta | C10: 1 | E10: Muito ruim | F10: 1
B13: SEGURO (custo) | C13: Nota | E13: PESO NO SCORE FINAL
B14: Baixo | C14: 5 | E14: Manutenção | F14: 0.4
B15: Médio | C15: 3 | E15: Consumo | F15: 0.35
B16: Alto | C16: 1 | E16: Seguro | F16: 0.25
E17: Soma (deve ser 100%) | F17: =F14+F15+F16 -> 1
B19: Como funciona
B20: Cada carro recebe uma nota de 1 a 5 em Manutenção, Consumo e Seguro, de acordo com as tabelas ao lado. O Score Final (0 a 10) é a média ponderada dessas três notas, usando os pesos definidos aqui. Preço não entra no score — ele é usado apenas para agrupar os carros por faixa de orçamento na aba 'Comparativo por Faixa'. Mude os pesos em azul para refletir o que é mais importante pra você: aumentar o peso de Consumo, por exemplo, favorece carros mais econômicos no ranking.

Sheet Base de Dados
A1: ← Capa | B1: RANKING COMPLETO — BASE DE DADOS
B2: Tabela mestre. Use as setas de filtro no cabeçalho para filtrar por faixa, manutenção, consumo etc.
B4: Rank Manual | C4: Modelo | D4: Preço mín (R$mil) | E4: Preço máx (R$mil) | F4: Faixa de preço | G4: Manutenção | H4: Consumo | I4: Seguro | J4: Pontos fortes | K4: Pontos fracos | L4: Recomendação | M4: Nota Manut. | N4: Nota Consumo | O4: Nota Seguro | P4: Score Final (0-10) | Q4: Faixa Orçamento | R4: Posição no Score | S4: Posição na Faixa
B5: 1 | C5: HB20 1.6 Manual 2017 | D5: 45 | E5: 60 | F5: R$45–60 mil | G5: Baixa | H5: Boa | I5: Médio | J5: Confiável, revenda, desempenho | K5: Preço maior que populares | L5: Melhor custo-benefício | M5: =IFERROR(INDEX(Metodologia!$C$6:$C$10,MATCH(G5,Metodologia!$B$6:$B$10,0)),0) -> 4 | N5: =IFERROR(INDEX(Metodologia!$F$6:$F$10,MATCH(H5,Metodologia!$E$6:$E$10,0)),0) -> 4 | O5: =IFERROR(INDEX(Metodologia!$C$14:$C$16,MATCH(I5,Metodologia!$B$14:$B$16,0)),0) -> 3 | P5: =ROUND((M5*Metodologia!$F$14+N5*Metodologia!$F$15+O5*Metodologia!$F$16)*2,1) -> 7.5 | Q5: =IF(D5<30,"Até R$30 mil",IF(D5<45,"R$30–45 mil",IF(D5<60,"R$45–60 mil","R$60 mil+"))) -> R$45–60 mil | R5: =RANK(P5,$P$5:$P$14,0)+COUNTIF($P$5:P5,P5)-1 -> 5 | S5: =SUMPRODUCT((Q$5:Q$14=Q5)*(R$5:R$14<R5))+1 -> 1
B6: 2 | C6: Onix LTZ 1.4 AT 2018 | D6: 50 | E6: 65 | F6: R$50–65 mil | G6: Baixa | H6: Boa | I6: Médio | J6: Automático, peças fáceis | K6: Exigir manutenção do câmbio | L6: Melhor automático | M6: =IFERROR(INDEX(Metodologia!$C$6:$C$10,MATCH(G6,Metodologia!$B$6:$B$10,0)),0) -> 4 | N6: =IFERROR(INDEX(Metodologia!$F$6:$F$10,MATCH(H6,Metodologia!$E$6:$E$10,0)),0) -> 4 | O6: =IFERROR(INDEX(Metodologia!$C$14:$C$16,MATCH(I6,Metodologia!$B$14:$B$16,0)),0) -> 3 | P6: =ROUND((M6*Metodologia!$F$14+N6*Metodologia!$F$15+O6*Metodologia!$F$16)*2,1) -> 7.5 | Q6: =IF(D6<30,"Até R$30 mil",IF(D6<45,"R$30–45 mil",IF(D6<60,"R$45–60 mil","R$60 mil+"))) -> R$45–60 mil | R6: =RANK(P6,$P$5:$P$14,0)+COUNTIF($P$5:P6,P6)-1 -> 6 | S6: =SUMPRODUCT((Q$5:Q$14=Q6)*(R$5:R$14<R6))+1 -> 2
B7: 3 | C7: Hyundai i30 | D7: 45 | E7: 60 | F7: R$45–60 mil | G7: Média | H7: Média | I7: Alto | J7: Conforto, motor 2.0, acabamento | K7: Consome mais | L7: Carro dos sonhos | M7: =IFERROR(INDEX(Metodologia!$C$6:$C$10,MATCH(G7,Metodologia!$B$6:$B$10,0)),0) -> 3 | N7: =IFERROR(INDEX(Metodologia!$F$6:$F$10,MATCH(H7,Metodologia!$E$6:$E$10,0)),0) -> 3 | O7: =IFERROR(INDEX(Metodologia!$C$14:$C$16,MATCH(I7,Metodologia!$B$14:$B$16,0)),0) -> 1 | P7: =ROUND((M7*Metodologia!$F$14+N7*Metodologia!$F$15+O7*Metodologia!$F$16)*2,1) -> 5 | Q7: =IF(D7<30,"Até R$30 mil",IF(D7<45,"R$30–45 mil",IF(D7<60,"R$45–60 mil","R$60 mil+"))) -> R$45–60 mil | R7: =RANK(P7,$P$5:$P$14,0)+COUNTIF($P$5:P7,P7)-1 -> 10 | S7: =SUMPRODUCT((Q$5:Q$14=Q7)*(R$5:R$14<R7))+1 -> 4
B8: 4 | C8: Fiat Argo 1.3 | D8: 55 | E8: 70 | F8: R$55–70 mil | G8: Baixa | H8: Boa | I8: Médio | J8: Motor Firefly, moderno | K8: Preço | L8: Ótimo diário | M8: =IFERROR(INDEX(Metodologia!$C$6:$C$10,MATCH(G8,Metodologia!$B$6:$B$10,0)),0) -> 4 | N8: =IFERROR(INDEX(Metodologia!$F$6:$F$10,MATCH(H8,Metodologia!$E$6:$E$10,0)),0) -> 4 | O8: =IFERROR(INDEX(Metodologia!$C$14:$C$16,MATCH(I8,Metodologia!$B$14:$B$16,0)),0) -> 3 | P8: =ROUND((M8*Metodologia!$F$14+N8*Metodologia!$F$15+O8*Metodologia!$F$16)*2,1) -> 7.5 | Q8: =IF(D8<30,"Até R$30 mil",IF(D8<45,"R$30–45 mil",IF(D8<60,"R$45–60 mil","R$60 mil+"))) -> R$45–60 mil | R8: =RANK(P8,$P$5:$P$14,0)+COUNTIF($P$5:P8,P8)-1 -> 7 | S8: =SUMPRODUCT((Q$5:Q$14=Q8)*(R$5:R$14<R8))+1 -> 3
B9: 5 | C9: Nissan Tiida 1.8 | D9: 30 | E9: 45 | F9: R$30–45 mil | G9: Baixa | H9: Média | I9: Médio | J9: Muito completo | K9: Revenda menor | L9: Excelente custo-benefício | M9: =IFERROR(INDEX(Metodologia!$C$6:$C$10,MATCH(G9,Metodologia!$B$6:$B$10,0)),0) -> 4 | N9: =IFERROR(INDEX(Metodologia!$F$6:$F$10,MATCH(H9,Metodologia!$E$6:$E$10,0)),0) -> 3 | O9: =IFERROR(INDEX(Metodologia!$C$14:$C$16,MATCH(I9,Metodologia!$B$14:$B$16,0)),0) -> 3 | P9: =ROUND((M9*Metodologia!$F$14+N9*Metodologia!$F$15+O9*Metodologia!$F$16)*2,1) -> 6.8 | Q9: =IF(D9<30,"Até R$30 mil",IF(D9<45,"R$30–45 mil",IF(D9<60,"R$45–60 mil","R$60 mil+"))) -> R$30–45 mil | R9: =RANK(P9,$P$5:$P$14,0)+COUNTIF($P$5:P9,P9)-1 -> 8 | S9: =SUMPRODUCT((Q$5:Q$14=Q9)*(R$5:R$14<R9))+1 -> 3
B10: 6 | C10: Kia Cerato 2010 | D10: 35 | E10: 45 | F10: R$35–45 mil | G10: Média | H10: Média | I10: Médio | J10: Bonito e confortável | K10: Peças acabamento | L10: Boa opção | M10: =IFERROR(INDEX(Metodologia!$C$6:$C$10,MATCH(G10,Metodologia!$B$6:$B$10,0)),0) -> 3 | N10: =IFERROR(INDEX(Metodologia!$F$6:$F$10,MATCH(H10,Metodologia!$E$6:$E$10,0)),0) -> 3 | O10: =IFERROR(INDEX(Metodologia!$C$14:$C$16,MATCH(I10,Metodologia!$B$14:$B$16,0)),0) -> 3 | P10: =ROUND((M10*Metodologia!$F$14+N10*Metodologia!$F$15+O10*Metodologia!$F$16)*2,1) -> 6 | Q10: =IF(D10<30,"Até R$30 mil",IF(D10<45,"R$30–45 mil",IF(D10<60,"R$45–60 mil","R$60 mil+"))) -> R$30–45 mil | R10: =RANK(P10,$P$5:$P$14,0)+COUNTIF($P$5:P10,P10)-1 -> 9 | S10: =SUMPRODUCT((Q$5:Q$14=Q10)*(R$5:R$14<R10))+1 -> 4
B11: 7 | C11: Honda Fit 2008/09 | D11: 35 | E11: 45 | F11: R$35–45 mil | G11: Muito baixa | H11: Excelente | I11: Baixo | J11: Durabilidade | K11: Visual | L11: Muito racional | M11: =IFERROR(INDEX(Metodologia!$C$6:$C$10,MATCH(G11,Metodologia!$B$6:$B$10,0)),0) -> 5 | N11: =IFERROR(INDEX(Metodologia!$F$6:$F$10,MATCH(H11,Metodologia!$E$6:$E$10,0)),0) -> 5 | O11: =IFERROR(INDEX(Metodologia!$C$14:$C$16,MATCH(I11,Metodologia!$B$14:$B$16,0)),0) -> 5 | P11: =ROUND((M11*Metodologia!$F$14+N11*Metodologia!$F$15+O11*Metodologia!$F$16)*2,1) -> 10 | Q11: =IF(D11<30,"Até R$30 mil",IF(D11<45,"R$30–45 mil",IF(D11<60,"R$45–60 mil","R$60 mil+"))) -> R$30–45 mil | R11: =RANK(P11,$P$5:$P$14,0)+COUNTIF($P$5:P11,P11)-1 -> 1 | S11: =SUMPRODUCT((Q$5:Q$14=Q11)*(R$5:R$14<R11))+1 -> 1
B12: 8 | C12: Uno Firefly | D12: 35 | E12: 45 | F12: R$35–45 mil | G12: Muito baixa | H12: Excelente | I12: Baixo | J12: Economia | K12: Acabamento simples | L12: Cidade | M12: =IFERROR(INDEX(Metodologia!$C$6:$C$10,MATCH(G12,Metodologia!$B$6:$B$10,0)),0) -> 5 | N12: =IFERROR(INDEX(Metodologia!$F$6:$F$10,MATCH(H12,Metodologia!$E$6:$E$10,0)),0) -> 5 | O12: =IFERROR(INDEX(Metodologia!$C$14:$C$16,MATCH(I12,Metodologia!$B$14:$B$16,0)),0) -> 5 | P12: =ROUND((M12*Metodologia!$F$14+N12*Metodologia!$F$15+O12*Metodologia!$F$16)*2,1) -> 10 | Q12: =IF(D12<30,"Até R$30 mil",IF(D12<45,"R$30–45 mil",IF(D12<60,"R$45–60 mil","R$60 mil+"))) -> R$30–45 mil | R12: =RANK(P12,$P$5:$P$14,0)+COUNTIF($P$5:P12,P12)-1 -> 2 | S12: =SUMPRODUCT((Q$5:Q$14=Q12)*(R$5:R$14<R12))+1 -> 2
B13: 9 | C13: Corsa Max | D13: 0 | E13: 30 | F13: Até R$30 mil | G13: Muito baixa | H13: Boa | I13: Baixo | J13: Peças baratas | K13: Projeto antigo | L13: Primeiro carro barato | M13: =IFERROR(INDEX(Metodologia!$C$6:$C$10,MATCH(G13,Metodologia!$B$6:$B$10,0)),0) -> 5 | N13: =IFERROR(INDEX(Metodologia!$F$6:$F$10,MATCH(H13,Metodologia!$E$6:$E$10,0)),0) -> 4 | O13: =IFERROR(INDEX(Metodologia!$C$14:$C$16,MATCH(I13,Metodologia!$B$14:$B$16,0)),0) -> 5 | P13: =ROUND((M13*Metodologia!$F$14+N13*Metodologia!$F$15+O13*Metodologia!$F$16)*2,1) -> 9.3 | Q13: =IF(D13<30,"Até R$30 mil",IF(D13<45,"R$30–45 mil",IF(D13<60,"R$45–60 mil","R$60 mil+"))) -> Até R$30 mil | R13: =RANK(P13,$P$5:$P$14,0)+COUNTIF($P$5:P13,P13)-1 -> 3 | S13: =SUMPRODUCT((Q$5:Q$14=Q13)*(R$5:R$14<R13))+1 -> 1
B14: 10 | C14: Palio Fire/Classic | D14: 0 | E14: 30 | F14: Até R$30 mil | G14: Muito baixa | H14: Boa | I14: Baixo | J14: Baixíssimo custo | K14: Conforto | L14: Última opção | M14: =IFERROR(INDEX(Metodologia!$C$6:$C$10,MATCH(G14,Metodologia!$B$6:$B$10,0)),0) -> 5 | N14: =IFERROR(INDEX(Metodologia!$F$6:$F$10,MATCH(H14,Metodologia!$E$6:$E$10,0)),0) -> 4 | O14: =IFERROR(INDEX(Metodologia!$C$14:$C$16,MATCH(I14,Metodologia!$B$14:$B$16,0)),0) -> 5 | P14: =ROUND((M14*Metodologia!$F$14+N14*Metodologia!$F$15+O14*Metodologia!$F$16)*2,1) -> 9.3 | Q14: =IF(D14<30,"Até R$30 mil",IF(D14<45,"R$30–45 mil",IF(D14<60,"R$45–60 mil","R$60 mil+"))) -> Até R$30 mil | R14: =RANK(P14,$P$5:$P$14,0)+COUNTIF($P$5:P14,P14)-1 -> 4 | S14: =SUMPRODUCT((Q$5:Q$14=Q14)*(R$5:R$14<R14))+1 -> 2

Sheet Comparativo por Faixa
A1: ← Capa
B2: COMPARATIVO POR FAIXA DE ORÇAMENTO
B3: Modelos agrupados por orçamento, ordenados do melhor para o pior score dentro de cada faixa.
B5: Até R$30 mil
B6: Pos. | C6: Modelo | D6: Manutenção | E6: Consumo | F6: Seguro | G6: Score | H6: Recomendação
B7: 1 | C7: =IFERROR(INDEX('Base de Dados'!$C$5:$C$14,(SUMPRODUCT(('Base de Dados'!$Q$5:$Q$14=TRIM($B$5))*('Base de Dados'!$S$5:$S$14=1)*ROW('Base de Dados'!$Q$5:$Q$14)))-4),"—") -> Corsa Max | D7: =IFERROR(INDEX('Base de Dados'!$G$5:$G$14,(SUMPRODUCT(('Base de Dados'!$Q$5:$Q$14=TRIM($B$5))*('Base de Dados'!$S$5:$S$14=1)*ROW('Base de Dados'!$Q$5:$Q$14)))-4),"") -> Muito baixa | E7: =IFERROR(INDEX('Base de Dados'!$H$5:$H$14,(SUMPRODUCT(('Base de Dados'!$Q$5:$Q$14=TRIM($B$5))*('Base de Dados'!$S$5:$S$14=1)*ROW('Base de Dados'!$Q$5:$Q$14)))-4),"") -> Boa | F7: =IFERROR(INDEX('Base de Dados'!$I$5:$I$14,(SUMPRODUCT(('Base de Dados'!$Q$5:$Q$14=TRIM($B$5))*('Base de Dados'!$S$5:$S$14=1)*ROW('Base de Dados'!$Q$5:$Q$14)))-4),"") -> Baixo | G7: =IFERROR(INDEX('Base de Dados'!$P$5:$P$14,(SUMPRODUCT(('Base de Dados'!$Q$5:$Q$14=TRIM($B$5))*('Base de Dados'!$S$5:$S$14=1)*ROW('Base de Dados'!$Q$5:$Q$14)))-4),"") -> 9.3 | H7: =IFERROR(INDEX('Base de Dados'!$L$5:$L$14,(SUMPRODUCT(('Base de Dados'!$Q$5:$Q$14=TRIM($B$5))*('Base de Dados'!$S$5:$S$14=1)*ROW('Base de Dados'!$Q$5:$Q$14)))-4),"") -> Primeiro carro barato
B8: 2 | C8: =IFERROR(INDEX('Base de Dados'!$C$5:$C$14,(SUMPRODUCT(('Base de Dados'!$Q$5:$Q$14=TRIM($B$5))*('Base de Dados'!$S$5:$S$14=2)*ROW('Base de Dados'!$Q$5:$Q$14)))-4),"—") -> Palio Fire/Classic | D8: =IFERROR(INDEX('Base de Dados'!$G$5:$G$14,(SUMPRODUCT(('Base de Dados'!$Q$5:$Q$14=TRIM($B$5))*('Base de Dados'!$S$5:$S$14=2)*ROW('Base de Dados'!$Q$5:$Q$14)))-4),"") -> Muito baixa | E8: =IFERROR(INDEX('Base de Dados'!$H$5:$H$14,(SUMPRODUCT(('Base de Dados'!$Q$5:$Q$14=TRIM($B$5))*('Base de Dados'!$S$5:$S$14=2)*ROW('Base de Dados'!$Q$5:$Q$14)))-4),"") -> Boa | F8: =IFERROR(INDEX('Base de Dados'!$I$5:$I$14,(SUMPRODUCT(('Base de Dados'!$Q$5:$Q$14=TRIM($B$5))*('Base de Dados'!$S$5:$S$14=2)*ROW('Base de Dados'!$Q$5:$Q$14)))-4),"") -> Baixo | G8: =IFERROR(INDEX('Base de Dados'!$P$5:$P$14,(SUMPRODUCT(('Base de Dados'!$Q$5:$Q$14=TRIM($B$5))*('Base de Dados'!$S$5:$S$14=2)*ROW('Base de Dados'!$Q$5:$Q$14)))-4),"") -> 9.3 | H8: =IFERROR(INDEX('Base de Dados'!$L$5:$L$14,(SUMPRODUCT(('Base de Dados'!$Q$5:$Q$14=TRIM($B$5))*('Base de Dados'!$S$5:$S$14=2)*ROW('Base de Dados'!$Q$5:$Q$14)))-4),"") -> Última opção
B9: 3 | C9: =IFERROR(INDEX('Base de Dados'!$C$5:$C$14,(SUMPRODUCT(('Base de Dados'!$Q$5:$Q$14=TRIM($B$5))*('Base de Dados'!$S$5:$S$14=3)*ROW('Base de Dados'!$Q$5:$Q$14)))-4),"—") -> — | D9: =IFERROR(INDEX('Base de Dados'!$G$5:$G$14,(SUMPRODUCT(('Base de Dados'!$Q$5:$Q$14=TRIM($B$5))*('Base de Dados'!$S$5:$S$14=3)*ROW('Base de Dados'!$Q$5:$Q$14)))-4),"") | E9: =IFERROR(INDEX('Base de Dados'!$H$5:$H$14,(SUMPRODUCT(('Base de Dados'!$Q$5:$Q$14=TRIM($B$5))*('Base de Dados'!$S$5:$S$14=3)*ROW('Base de Dados'!$Q$5:$Q$14)))-4),"") | F9: =IFERROR(INDEX('Base de Dados'!$I$5:$I$14,(SUMPRODUCT(('Base de Dados'!$Q$5:$Q$14=TRIM($B$5))*('Base de Dados'!$S$5:$S$14=3)*ROW('Base de Dados'!$Q$5:$Q$14)))-4),"") | G9: =IFERROR(INDEX('Base de Dados'!$P$5:$P$14,(SUMPRODUCT(('Base de Dados'!$Q$5:$Q$14=TRIM($B$5))*('Base de Dados'!$S$5:$S$14=3)*ROW('Base de Dados'!$Q$5:$Q$14)))-4),"") | H9: =IFERROR(INDEX('Base de Dados'!$L$5:$L$14,(SUMPRODUCT(('Base de Dados'!$Q$5:$Q$14=TRIM($B$5))*('Base de Dados'!$S$5:$S$14=3)*ROW('Base de Dados'!$Q$5:$Q$14)))-4),"")
B10: 4 | C10: =IFERROR(INDEX('Base de Dados'!$C$5:$C$14,(SUMPRODUCT(('Base de Dados'!$Q$5:$Q$14=TRIM($B$5))*('Base de Dados'!$S$5:$S$14=4)*ROW('Base de Dados'!$Q$5:$Q$14)))-4),"—") -> — | D10: =IFERROR(INDEX('Base de Dados'!$G$5:$G$14,(SUMPRODUCT(('Base de Dados'!$Q$5:$Q$14=TRIM($B$5))*('Base de Dados'!$S$5:$S$14=4)*ROW('Base de Dados'!$Q$5:$Q$14)))-4),"") | E10: =IFERROR(INDEX('Base de Dados'!$H$5:$H$14,(SUMPRODUCT(('Base de Dados'!$Q$5:$Q$14=TRIM($B$5))*('Base de Dados'!$S$5:$S$14=4)*ROW('Base de Dados'!$Q$5:$Q$14)))-4),"") | F10: =IFERROR(INDEX('Base de Dados'!$I$5:$I$14,(SUMPRODUCT(('Base de Dados'!$Q$5:$Q$14=TRIM($B$5))*('Base de Dados'!$S$5:$S$14=4)*ROW('Base de Dados'!$Q$5:$Q$14)))-4),"") | G10: =IFERROR(INDEX('Base de Dados'!$P$5:$P$14,(SUMPRODUCT(('Base de Dados'!$Q$5:$Q$14=TRIM($B$5))*('Base de Dados'!$S$5:$S$14=4)*ROW('Base de Dados'!$Q$5:$Q$14)))-4),"") | H10: =IFERROR(INDEX('Base de Dados'!$L$5:$L$14,(SUMPRODUCT(('Base de Dados'!$Q$5:$Q$14=TRIM($B$5))*('Base de Dados'!$S$5:$S$14=4)*ROW('Base de Dados'!$Q$5:$Q$14)))-4),"")
B12: R$30–45 mil
B13: Pos. | C13: Modelo | D13: Manutenção | E13: Consumo | F13: Seguro | G13: Score | H13: Recomendação
B14: 1 | C14: =IFERROR(INDEX('Base de Dados'!$C$5:$C$14,(SUMPRODUCT(('Base de Dados'!$Q$5:$Q$14=TRIM($B$12))*('Base de Dados'!$S$5:$S$14=1)*ROW('Base de Dados'!$Q$5:$Q$14)))-4),"—") -> Honda Fit 2008/09 | D14: =IFERROR(INDEX('Base de Dados'!$G$5:$G$14,(SUMPRODUCT(('Base de Dados'!$Q$5:$Q$14=TRIM($B$12))*('Base de Dados'!$S$5:$S$14=1)*ROW('Base de Dados'!$Q$5:$Q$14)))-4),"") -> Muito baixa | E14: =IFERROR(INDEX('Base de Dados'!$H$5:$H$14,(SUMPRODUCT(('Base de Dados'!$Q$5:$Q$14=TRIM($B$12))*('Base de Dados'!$S$5:$S$14=1)*ROW('Base de Dados'!$Q$5:$Q$14)))-4),"") -> Excelente | F14: =IFERROR(INDEX('Base de Dados'!$I$5:$I$14,(SUMPRODUCT(('Base de Dados'!$Q$5:$Q$14=TRIM($B$12))*('Base de Dados'!$S$5:$S$14=1)*ROW('Base de Dados'!$Q$5:$Q$14)))-4),"") -> Baixo | G14: =IFERROR(INDEX('Base de Dados'!$P$5:$P$14,(SUMPRODUCT(('Base de Dados'!$Q$5:$Q$14=TRIM($B$12))*('Base de Dados'!$S$5:$S$14=1)*ROW('Base de Dados'!$Q$5:$Q$14)))-4),"") -> 10 | H14: =IFERROR(INDEX('Base de Dados'!$L$5:$L$14,(SUMPRODUCT(('Base de Dados'!$Q$5:$Q$14=TRIM($B$12))*('Base de Dados'!$S$5:$S$14=1)*ROW('Base de Dados'!$Q$5:$Q$14)))-4),"") -> Muito racional
B15: 2 | C15: =IFERROR(INDEX('Base de Dados'!$C$5:$C$14,(SUMPRODUCT(('Base de Dados'!$Q$5:$Q$14=TRIM($B$12))*('Base de Dados'!$S$5:$S$14=2)*ROW('Base de Dados'!$Q$5:$Q$14)))-4),"—") -> Uno Firefly | D15: =IFERROR(INDEX('Base de Dados'!$G$5:$G$14,(SUMPRODUCT(('Base de Dados'!$Q$5:$Q$14=TRIM($B$12))*('Base de Dados'!$S$5:$S$14=2)*ROW('Base de Dados'!$Q$5:$Q$14)))-4),"") -> Muito baixa | E15: =IFERROR(INDEX('Base de Dados'!$H$5:$H$14,(SUMPRODUCT(('Base de Dados'!$Q$5:$Q$14=TRIM($B$12))*('Base de Dados'!$S$5:$S$14=2)*ROW('Base de Dados'!$Q$5:$Q$14)))-4),"") -> Excelente | F15: =IFERROR(INDEX('Base de Dados'!$I$5:$I$14,(SUMPRODUCT(('Base de Dados'!$Q$5:$Q$14=TRIM($B$12))*('Base de Dados'!$S$5:$S$14=2)*ROW('Base de Dados'!$Q$5:$Q$14)))-4),"") -> Baixo | G15: =IFERROR(INDEX('Base de Dados'!$P$5:$P$14,(SUMPRODUCT(('Base de Dados'!$Q$5:$Q$14=TRIM($B$12))*('Base de Dados'!$S$5:$S$14=2)*ROW('Base de Dados'!$Q$5:$Q$14)))-4),"") -> 10 | H15: =IFERROR(INDEX('Base de Dados'!$L$5:$L$14,(SUMPRODUCT(('Base de Dados'!$Q$5:$Q$14=TRIM($B$12))*('Base de Dados'!$S$5:$S$14=2)*ROW('Base de Dados'!$Q$5:$Q$14)))-4),"") -> Cidade
B16: 3 | C16: =IFERROR(INDEX('Base de Dados'!$C$5:$C$14,(SUMPRODUCT(('Base de Dados'!$Q$5:$Q$14=TRIM($B$12))*('Base de Dados'!$S$5:$S$14=3)*ROW('Base de Dados'!$Q$5:$Q$14)))-4),"—") -> Nissan Tiida 1.8 | D16: =IFERROR(INDEX('Base de Dados'!$G$5:$G$14,(SUMPRODUCT(('Base de Dados'!$Q$5:$Q$14=TRIM($B$12))*('Base de Dados'!$S$5:$S$14=3)*ROW('Base de Dados'!$Q$5:$Q$14)))-4),"") -> Baixa | E16: =IFERROR(INDEX('Base de Dados'!$H$5:$H$14,(SUMPRODUCT(('Base de Dados'!$Q$5:$Q$14=TRIM($B$12))*('Base de Dados'!$S$5:$S$14=3)*ROW('Base de Dados'!$Q$5:$Q$14)))-4),"") -> Média | F16: =IFERROR(INDEX('Base de Dados'!$I$5:$I$14,(SUMPRODUCT(('Base de Dados'!$Q$5:$Q$14=TRIM($B$12))*('Base de Dados'!$S$5:$S$14=3)*ROW('Base de Dados'!$Q$5:$Q$14)))-4),"") -> Médio | G16: =IFERROR(INDEX('Base de Dados'!$P$5:$P$14,(SUMPRODUCT(('Base de Dados'!$Q$5:$Q$14=TRIM($B$12))*('Base de Dados'!$S$5:$S$14=3)*ROW('Base de Dados'!$Q$5:$Q$14)))-4),"") -> 6.8 | H16: =IFERROR(INDEX('Base de Dados'!$L$5:$L$14,(SUMPRODUCT(('Base de Dados'!$Q$5:$Q$14=TRIM($B$12))*('Base de Dados'!$S$5:$S$14=3)*ROW('Base de Dados'!$Q$5:$Q$14)))-4),"") -> Excelente custo-benefício
B17: 4 | C17: =IFERROR(INDEX('Base de Dados'!$C$5:$C$14,(SUMPRODUCT(('Base de Dados'!$Q$5:$Q$14=TRIM($B$12))*('Base de Dados'!$S$5:$S$14=4)*ROW('Base de Dados'!$Q$5:$Q$14)))-4),"—") -> Kia Cerato 2010 | D17: =IFERROR(INDEX('Base de Dados'!$G$5:$G$14,(SUMPRODUCT(('Base de Dados'!$Q$5:$Q$14=TRIM($B$12))*('Base de Dados'!$S$5:$S$14=4)*ROW('Base de Dados'!$Q$5:$Q$14)))-4),"") -> Média | E17: =IFERROR(INDEX('Base de Dados'!$H$5:$H$14,(SUMPRODUCT(('Base de Dados'!$Q$5:$Q$14=TRIM($B$12))*('Base de Dados'!$S$5:$S$14=4)*ROW('Base de Dados'!$Q$5:$Q$14)))-4),"") -> Média | F17: =IFERROR(INDEX('Base de Dados'!$I$5:$I$14,(SUMPRODUCT(('Base de Dados'!$Q$5:$Q$14=TRIM($B$12))*('Base de Dados'!$S$5:$S$14=4)*ROW('Base de Dados'!$Q$5:$Q$14)))-4),"") -> Médio | G17: =IFERROR(INDEX('Base de Dados'!$P$5:$P$14,(SUMPRODUCT(('Base de Dados'!$Q$5:$Q$14=TRIM($B$12))*('Base de Dados'!$S$5:$S$14=4)*ROW('Base de Dados'!$Q$5:$Q$14)))-4),"") -> 6 | H17: =IFERROR(INDEX('Base de Dados'!$L$5:$L$14,(SUMPRODUCT(('Base de Dados'!$Q$5:$Q$14=TRIM($B$12))*('Base de Dados'!$S$5:$S$14=4)*ROW('Base de Dados'!$Q$5:$Q$14)))-4),"") -> Boa opção
B19: R$45–60 mil
B20: Pos. | C20: Modelo | D20: Manutenção | E20: Consumo | F20: Seguro | G20: Score | H20: Recomendação
B21: 1 | C21: =IFERROR(INDEX('Base de Dados'!$C$5:$C$14,(SUMPRODUCT(('Base de Dados'!$Q$5:$Q$14=TRIM($B$19))*('Base de Dados'!$S$5:$S$14=1)*ROW('Base de Dados'!$Q$5:$Q$14)))-4),"—") -> HB20 1.6 Manual 2017 | D21: =IFERROR(INDEX('Base de Dados'!$G$5:$G$14,(SUMPRODUCT(('Base de Dados'!$Q$5:$Q$14=TRIM($B$19))*('Base de Dados'!$S$5:$S$14=1)*ROW('Base de Dados'!$Q$5:$Q$14)))-4),"") -> Baixa | E21: =IFERROR(INDEX('Base de Dados'!$H$5:$H$14,(SUMPRODUCT(('Base de Dados'!$Q$5:$Q$14=TRIM($B$19))*('Base de Dados'!$S$5:$S$14=1)*ROW('Base de Dados'!$Q$5:$Q$14)))-4),"") -> Boa | F21: =IFERROR(INDEX('Base de Dados'!$I$5:$I$14,(SUMPRODUCT(('Base de Dados'!$Q$5:$Q$14=TRIM($B$19))*('Base de Dados'!$S$5:$S$14=1)*ROW('Base de Dados'!$Q$5:$Q$14)))-4),"") -> Médio | G21: =IFERROR(INDEX('Base de Dados'!$P$5:$P$14,(SUMPRODUCT(('Base de Dados'!$Q$5:$Q$14=TRIM($B$19))*('Base de Dados'!$S$5:$S$14=1)*ROW('Base de Dados'!$Q$5:$Q$14)))-4),"") -> 7.5 | H21: =IFERROR(INDEX('Base de Dados'!$L$5:$L$14,(SUMPRODUCT(('Base de Dados'!$Q$5:$Q$14=TRIM($B$19))*('Base de Dados'!$S$5:$S$14=1)*ROW('Base de Dados'!$Q$5:$Q$14)))-4),"") -> Melhor custo-benefício
B22: 2 | C22: =IFERROR(INDEX('Base de Dados'!$C$5:$C$14,(SUMPRODUCT(('Base de Dados'!$Q$5:$Q$14=TRIM($B$19))*('Base de Dados'!$S$5:$S$14=2)*ROW('Base de Dados'!$Q$5:$Q$14)))-4),"—") -> Onix LTZ 1.4 AT 2018 | D22: =IFERROR(INDEX('Base de Dados'!$G$5:$G$14,(SUMPRODUCT(('Base de Dados'!$Q$5:$Q$14=TRIM($B$19))*('Base de Dados'!$S$5:$S$14=2)*ROW('Base de Dados'!$Q$5:$Q$14)))-4),"") -> Baixa | E22: =IFERROR(INDEX('Base de Dados'!$H$5:$H$14,(SUMPRODUCT(('Base de Dados'!$Q$5:$Q$14=TRIM($B$19))*('Base de Dados'!$S$5:$S$14=2)*ROW('Base de Dados'!$Q$5:$Q$14)))-4),"") -> Boa | F22: =IFERROR(INDEX('Base de Dados'!$I$5:$I$14,(SUMPRODUCT(('Base de Dados'!$Q$5:$Q$14=TRIM($B$19))*('Base de Dados'!$S$5:$S$14=2)*ROW('Base de Dados'!$Q$5:$Q$14)))-4),"") -> Médio | G22: =IFERROR(INDEX('Base de Dados'!$P$5:$P$14,(SUMPRODUCT(('Base de Dados'!$Q$5:$Q$14=TRIM($B$19))*('Base de Dados'!$S$5:$S$14=2)*ROW('Base de Dados'!$Q$5:$Q$14)))-4),"") -> 7.5 | H22: =IFERROR(INDEX('Base de Dados'!$L$5:$L$14,(SUMPRODUCT(('Base de Dados'!$Q$5:$Q$14=TRIM($B$19))*('Base de Dados'!$S$5:$S$14=2)*ROW('Base de Dados'!$Q$5:$Q$14)))-4),"") -> Melhor automático
B23: 3 | C23: =IFERROR(INDEX('Base de Dados'!$C$5:$C$14,(SUMPRODUCT(('Base de Dados'!$Q$5:$Q$14=TRIM($B$19))*('Base de Dados'!$S$5:$S$14=3)*ROW('Base de Dados'!$Q$5:$Q$14)))-4),"—") -> Fiat Argo 1.3 | D23: =IFERROR(INDEX('Base de Dados'!$G$5:$G$14,(SUMPRODUCT(('Base de Dados'!$Q$5:$Q$14=TRIM($B$19))*('Base de Dados'!$S$5:$S$14=3)*ROW('Base de Dados'!$Q$5:$Q$14)))-4),"") -> Baixa | E23: =IFERROR(INDEX('Base de Dados'!$H$5:$H$14,(SUMPRODUCT(('Base de Dados'!$Q$5:$Q$14=TRIM($B$19))*('Base de Dados'!$S$5:$S$14=3)*ROW('Base de Dados'!$Q$5:$Q$14)))-4),"") -> Boa | F23: =IFERROR(INDEX('Base de Dados'!$I$5:$I$14,(SUMPRODUCT(('Base de Dados'!$Q$5:$Q$14=TRIM($B$19))*('Base de Dados'!$S$5:$S$14=3)*ROW('Base de Dados'!$Q$5:$Q$14)))-4),"") -> Médio | G23: =IFERROR(INDEX('Base de Dados'!$P$5:$P$14,(SUMPRODUCT(('Base de Dados'!$Q$5:$Q$14=TRIM($B$19))*('Base de Dados'!$S$5:$S$14=3)*ROW('Base de Dados'!$Q$5:$Q$14)))-4),"") -> 7.5 | H23: =IFERROR(INDEX('Base de Dados'!$L$5:$L$14,(SUMPRODUCT(('Base de Dados'!$Q$5:$Q$14=TRIM($B$19))*('Base de Dados'!$S$5:$S$14=3)*ROW('Base de Dados'!$Q$5:$Q$14)))-4),"") -> Ótimo diário
B24: 4 | C24: =IFERROR(INDEX('Base de Dados'!$C$5:$C$14,(SUMPRODUCT(('Base de Dados'!$Q$5:$Q$14=TRIM($B$19))*('Base de Dados'!$S$5:$S$14=4)*ROW('Base de Dados'!$Q$5:$Q$14)))-4),"—") -> Hyundai i30 | D24: =IFERROR(INDEX('Base de Dados'!$G$5:$G$14,(SUMPRODUCT(('Base de Dados'!$Q$5:$Q$14=TRIM($B$19))*('Base de Dados'!$S$5:$S$14=4)*ROW('Base de Dados'!$Q$5:$Q$14)))-4),"") -> Média | E24: =IFERROR(INDEX('Base de Dados'!$H$5:$H$14,(SUMPRODUCT(('Base de Dados'!$Q$5:$Q$14=TRIM($B$19))*('Base de Dados'!$S$5:$S$14=4)*ROW('Base de Dados'!$Q$5:$Q$14)))-4),"") -> Média | F24: =IFERROR(INDEX('Base de Dados'!$I$5:$I$14,(SUMPRODUCT(('Base de Dados'!$Q$5:$Q$14=TRIM($B$19))*('Base de Dados'!$S$5:$S$14=4)*ROW('Base de Dados'!$Q$5:$Q$14)))-4),"") -> Alto | G24: =IFERROR(INDEX('Base de Dados'!$P$5:$P$14,(SUMPRODUCT(('Base de Dados'!$Q$5:$Q$14=TRIM($B$19))*('Base de Dados'!$S$5:$S$14=4)*ROW('Base de Dados'!$Q$5:$Q$14)))-4),"") -> 5 | H24: =IFERROR(INDEX('Base de Dados'!$L$5:$L$14,(SUMPRODUCT(('Base de Dados'!$Q$5:$Q$14=TRIM($B$19))*('Base de Dados'!$S$5:$S$14=4)*ROW('Base de Dados'!$Q$5:$Q$14)))-4),"") -> Carro dos sonhos
B26: R$60 mil+
B27: Pos. | C27: Modelo | D27: Manutenção | E27: Consumo | F27: Seguro | G27: Score | H27: Recomendação
B28: 1 | C28: =IFERROR(INDEX('Base de Dados'!$C$5:$C$14,(SUMPRODUCT(('Base de Dados'!$Q$5:$Q$14=TRIM($B$26))*('Base de Dados'!$S$5:$S$14=1)*ROW('Base de Dados'!$Q$5:$Q$14)))-4),"—") -> — | D28: =IFERROR(INDEX('Base de Dados'!$G$5:$G$14,(SUMPRODUCT(('Base de Dados'!$Q$5:$Q$14=TRIM($B$26))*('Base de Dados'!$S$5:$S$14=1)*ROW('Base de Dados'!$Q$5:$Q$14)))-4),"") | E28: =IFERROR(INDEX('Base de Dados'!$H$5:$H$14,(SUMPRODUCT(('Base de Dados'!$Q$5:$Q$14=TRIM($B$26))*('Base de Dados'!$S$5:$S$14=1)*ROW('Base de Dados'!$Q$5:$Q$14)))-4),"") | F28: =IFERROR(INDEX('Base de Dados'!$I$5:$I$14,(SUMPRODUCT(('Base de Dados'!$Q$5:$Q$14=TRIM($B$26))*('Base de Dados'!$S$5:$S$14=1)*ROW('Base de Dados'!$Q$5:$Q$14)))-4),"") | G28: =IFERROR(INDEX('Base de Dados'!$P$5:$P$14,(SUMPRODUCT(('Base de Dados'!$Q$5:$Q$14=TRIM($B$26))*('Base de Dados'!$S$5:$S$14=1)*ROW('Base de Dados'!$Q$5:$Q$14)))-4),"") | H28: =IFERROR(INDEX('Base de Dados'!$L$5:$L$14,(SUMPRODUCT(('Base de Dados'!$Q$5:$Q$14=TRIM($B$26))*('Base de Dados'!$S$5:$S$14=1)*ROW('Base de Dados'!$Q$5:$Q$14)))-4),"")
B29: 2 | C29: =IFERROR(INDEX('Base de Dados'!$C$5:$C$14,(SUMPRODUCT(('Base de Dados'!$Q$5:$Q$14=TRIM($B$26))*('Base de Dados'!$S$5:$S$14=2)*ROW('Base de Dados'!$Q$5:$Q$14)))-4),"—") -> — | D29: =IFERROR(INDEX('Base de Dados'!$G$5:$G$14,(SUMPRODUCT(('Base de Dados'!$Q$5:$Q$14=TRIM($B$26))*('Base de Dados'!$S$5:$S$14=2)*ROW('Base de Dados'!$Q$5:$Q$14)))-4),"") | E29: =IFERROR(INDEX('Base de Dados'!$H$5:$H$14,(SUMPRODUCT(('Base de Dados'!$Q$5:$Q$14=TRIM($B$26))*('Base de Dados'!$S$5:$S$14=2)*ROW('Base de Dados'!$Q$5:$Q$14)))-4),"") | F29: =IFERROR(INDEX('Base de Dados'!$I$5:$I$14,(SUMPRODUCT(('Base de Dados'!$Q$5:$Q$14=TRIM($B$26))*('Base de Dados'!$S$5:$S$14=2)*ROW('Base de Dados'!$Q$5:$Q$14)))-4),"") | G29: =IFERROR(INDEX('Base de Dados'!$P$5:$P$14,(SUMPRODUCT(('Base de Dados'!$Q$5:$Q$14=TRIM($B$26))*('Base de Dados'!$S$5:$S$14=2)*ROW('Base de Dados'!$Q$5:$Q$14)))-4),"") | H29: =IFERROR(INDEX('Base de Dados'!$L$5:$L$14,(SUMPRODUCT(('Base de Dados'!$Q$5:$Q$14=TRIM($B$26))*('Base de Dados'!$S$5:$S$14=2)*ROW('Base de Dados'!$Q$5:$Q$14)))-4),"")
B30: 3 | C30: =IFERROR(INDEX('Base de Dados'!$C$5:$C$14,(SUMPRODUCT(('Base de Dados'!$Q$5:$Q$14=TRIM($B$26))*('Base de Dados'!$S$5:$S$14=3)*ROW('Base de Dados'!$Q$5:$Q$14)))-4),"—") -> — | D30: =IFERROR(INDEX('Base de Dados'!$G$5:$G$14,(SUMPRODUCT(('Base de Dados'!$Q$5:$Q$14=TRIM($B$26))*('Base de Dados'!$S$5:$S$14=3)*ROW('Base de Dados'!$Q$5:$Q$14)))-4),"") | E30: =IFERROR(INDEX('Base de Dados'!$H$5:$H$14,(SUMPRODUCT(('Base de Dados'!$Q$5:$Q$14=TRIM($B$26))*('Base de Dados'!$S$5:$S$14=3)*ROW('Base de Dados'!$Q$5:$Q$14)))-4),"") | F30: =IFERROR(INDEX('Base de Dados'!$I$5:$I$14,(SUMPRODUCT(('Base de Dados'!$Q$5:$Q$14=TRIM($B$26))*('Base de Dados'!$S$5:$S$14=3)*ROW('Base de Dados'!$Q$5:$Q$14)))-4),"") | G30: =IFERROR(INDEX('Base de Dados'!$P$5:$P$14,(SUMPRODUCT(('Base de Dados'!$Q$5:$Q$14=TRIM($B$26))*('Base de Dados'!$S$5:$S$14=3)*ROW('Base de Dados'!$Q$5:$Q$14)))-4),"") | H30: =IFERROR(INDEX('Base de Dados'!$L$5:$L$14,(SUMPRODUCT(('Base de Dados'!$Q$5:$Q$14=TRIM($B$26))*('Base de Dados'!$S$5:$S$14=3)*ROW('Base de Dados'!$Q$5:$Q$14)))-4),"")
B31: 4 | C31: =IFERROR(INDEX('Base de Dados'!$C$5:$C$14,(SUMPRODUCT(('Base de Dados'!$Q$5:$Q$14=TRIM($B$26))*('Base de Dados'!$S$5:$S$14=4)*ROW('Base de Dados'!$Q$5:$Q$14)))-4),"—") -> — | D31: =IFERROR(INDEX('Base de Dados'!$G$5:$G$14,(SUMPRODUCT(('Base de Dados'!$Q$5:$Q$14=TRIM($B$26))*('Base de Dados'!$S$5:$S$14=4)*ROW('Base de Dados'!$Q$5:$Q$14)))-4),"") | E31: =IFERROR(INDEX('Base de Dados'!$H$5:$H$14,(SUMPRODUCT(('Base de Dados'!$Q$5:$Q$14=TRIM($B$26))*('Base de Dados'!$S$5:$S$14=4)*ROW('Base de Dados'!$Q$5:$Q$14)))-4),"") | F31: =IFERROR(INDEX('Base de Dados'!$I$5:$I$14,(SUMPRODUCT(('Base de Dados'!$Q$5:$Q$14=TRIM($B$26))*('Base de Dados'!$S$5:$S$14=4)*ROW('Base de Dados'!$Q$5:$Q$14)))-4),"") | G31: =IFERROR(INDEX('Base de Dados'!$P$5:$P$14,(SUMPRODUCT(('Base de Dados'!$Q$5:$Q$14=TRIM($B$26))*('Base de Dados'!$S$5:$S$14=4)*ROW('Base de Dados'!$Q$5:$Q$14)))-4),"") | H31: =IFERROR(INDEX('Base de Dados'!$L$5:$L$14,(SUMPRODUCT(('Base de Dados'!$Q$5:$Q$14=TRIM($B$26))*('Base de Dados'!$S$5:$S$14=4)*ROW('Base de Dados'!$Q$5:$Q$14)))-4),"")

Sheet Ficha Individual
A1: ← Capa
B2: FICHA INDIVIDUAL DO VEÍCULO
B3: Selecione um modelo na lista para ver a ficha completa.
B5: Escolha o modelo: | C5: Hyundai i30
B7: Faixa de preço | C7: =INDEX('Base de Dados'!$F$5:$F$14,MATCH($C$5,'Base de Dados'!$C$5:$C$14,0)) -> R$45–60 mil
B8: Manutenção | C8: =INDEX('Base de Dados'!$G$5:$G$14,MATCH($C$5,'Base de Dados'!$C$5:$C$14,0)) -> Média
B9: Consumo | C9: =INDEX('Base de Dados'!$H$5:$H$14,MATCH($C$5,'Base de Dados'!$C$5:$C$14,0)) -> Média
B10: Seguro | C10: =INDEX('Base de Dados'!$I$5:$I$14,MATCH($C$5,'Base de Dados'!$C$5:$C$14,0)) -> Alto
B11: Score Final (0-10) | C11: =INDEX('Base de Dados'!$P$5:$P$14,MATCH($C$5,'Base de Dados'!$C$5:$C$14,0)) -> 5
B12: Posição no ranking geral | C12: =INDEX('Base de Dados'!$R$5:$R$14,MATCH($C$5,'Base de Dados'!$C$5:$C$14,0)) -> 10
B13: Faixa de orçamento | C13: =INDEX('Base de Dados'!$Q$5:$Q$14,MATCH($C$5,'Base de Dados'!$C$5:$C$14,0)) -> R$45–60 mil
B14: Pontos fortes | C14: =INDEX('Base de Dados'!$J$5:$J$14,MATCH($C$5,'Base de Dados'!$C$5:$C$14,0)) -> Conforto, motor 2.0, acabamento
B15: Pontos fracos | C15: =INDEX('Base de Dados'!$K$5:$K$14,MATCH($C$5,'Base de Dados'!$C$5:$C$14,0)) -> Consome mais
B16: Recomendação | C16: =INDEX('Base de Dados'!$L$5:$L$14,MATCH($C$5,'Base de Dados'!$C$5:$C$14,0)) -> Carro dos sonhos

Sheet Parecer Técnico
A1: ← Capa
B2: SE EU FOSSE COMPRAR — PARECER POR FAIXA DE ORÇAMENTO
B3: O nome e o score abaixo são puxados automaticamente do ranking — atualizam se você editar a base ou os pesos.
B5: Até R$30 mil
B6: =" Recomendação automática do ranking: "&'Comparativo por Faixa'!C7 -> Recomendação automática do ranking: Corsa Max
B7: Nessa faixa o critério manda é confiabilidade mecânica com o menor risco possível de dor de cabeça — não dá pra esperar conforto ou acabamento. Corsa Max e Palio Fire/Classic dominam por peças baratas e manutenção muito baixa, mas são projetos antigos: revisão pré-compra rigorosa (suspensão, câmbio, motor) é obrigatória. Serve como primeiro carro ou carro de uso leve, não para quem roda muito por dia.
B12: R$30–45 mil
B13: =" Recomendação automática do ranking: "&'Comparativo por Faixa'!C14 -> Recomendação automática do ranking: Honda Fit 2008/09
B14: Essa é a faixa com melhor equilíbrio da lista. Honda Fit e Uno Firefly empatam no score mais alto do levantamento inteiro — durabilidade muito alta, consumo excelente e seguro barato. Se o critério é racionalidade pura (gastar pouco e rodar tranquilo), a escolha está aqui, não na faixa de cima.
B19: R$45–60 mil
B20: =" Recomendação automática do ranking: "&'Comparativo por Faixa'!C21 -> Recomendação automática do ranking: HB20 1.6 Manual 2017
B21: HB20, Onix e Argo aparecem tecnicamente empatados nessa faixa — a escolha entre eles vira uma questão de preferência pessoal (câmbio automático pesa a favor do Onix, revenda pesa a favor do HB20). O Hyundai i30 fica de fora do topo do score porque consome mais e tem seguro mais caro — ele entra aqui pelo desejo, não pelo custo-benefício, e isso precisa estar claro antes de decidir.
B26: Conclusão geral
B27: Olhando os três blocos, o salto de qualidade real está entre 'Até R$30 mil' e 'R$30–45 mil' — com pouco mais de investimento, sobe muito o nível de confiabilidade (Honda Fit e Uno Firefly). Já o salto de 'R$30–45 mil' para 'R$45–60 mil' entrega mais conforto e categoria, mas não necessariamente mais confiabilidade — é uma troca de racionalidade por desejo, o que é uma decisão válida, desde que consciente.

Sheet Fontes e Notas
A1: ← Capa
B2: FONTES E NOTAS METODOLÓGICAS
B4: Origem dos dados
B5: Avaliação qualitativa (Manutenção, Consumo, Seguro, Pontos fortes/fracos e Recomendação) fornecida diretamente pelo usuário, com base em experiência prática e pesquisa própria sobre os modelos — não são dados de uma tabela oficial FIPE ou de seguradora.
B8: Faixas de preço
B9: Extraídas do texto original de cada carro (ex.: 'R$45–60 mil') e convertidas em valores numéricos mínimo e máximo para permitir o agrupamento automático por faixa de orçamento.
B12: Cálculo do Score Final
B13: Nota ponderada (0 a 10) combinando Manutenção, Consumo e Seguro conforme tabelas de conversão e pesos definidos na aba 'Metodologia'. Esses pesos são uma escolha subjetiva (editável) e não uma fórmula de mercado — mudar os pesos muda o ranking.
B16: Preço não entra no score
B17: O preço é usado apenas para agrupar os carros nas faixas de orçamento, não para pontuar 'custo-benefício' dentro do score — isso evita distorcer a nota de confiabilidade com o valor do carro.
B20: Limitação importante
B21: Esta planilha reflete uma curadoria pessoal, não um levantamento estatístico de mercado. Antes de qualquer compra, uma vistoria mecânica presencial no carro específico é obrigatória — o modelo pode ter nota alta e a unidade individual estar com problema.
B24: Atualização
B25: Para adicionar um carro novo, insira uma linha na tabela da aba 'Base de Dados' (dentro do intervalo da tabela 'TabelaCarros') preenchendo as colunas B a L — as colunas de nota e score se calculam sozinhas.
